[
  {
    "tipo": "voz_personalizada",
    "direccion": "toB",
    "lat": 40.420112,
    "lng": -3.692313,
    "radio_metros": 60,
    "icono_sf": "arrow.up",
    "mensaje": "Línea n 4 en sentido barajas",
    "distancia_previa_metros": 110,
    "mensaje_previo": ""
  },
  {
    "tipo": "voz_personalizada",
    "direccion": "toB",
    "lat": 40.423367,
    "lng": -3.690852,
    "radio_metros": 60,
    "icono_sf": "arrow.turn.up.right",
    "mensaje": "Parada , con giro a la derecha en dirección jorge juan",
    "distancia_previa_metros": 110,
    "mensaje_previo": ""
  },
  {
    "tipo": "voz_personalizada",
    "direccion": "toB",
    "lat": 40.424112,
    "lng": -3.688635,
    "radio_metros": 60,
    "icono_sf": "arrow.up",
    "mensaje": "continuamos recto hasta calle de velázquez no hay paradas",
    "distancia_previa_metros": 110,
    "mensaje_previo": ""
  },
  {
    "tipo": "voz_personalizada",
    "direccion": "toB",
    "lat": 40.42382,
    "lng": -3.684897,
    "radio_metros": 60,
    "icono_sf": "light.beacon.max.fill",
    "mensaje": "En semáforo giramos a la izquierda y continuamos por calle de velázquez",
    "distancia_previa_metros": 110,
    "mensaje_previo": ""
  },
  {
    "tipo": "voz_personalizada",
    "direccion": "toB",
    "lat": 40.424668,
    "lng": -3.684185,
    "radio_metros": 60,
    "icono_sf": "arrow.up",
    "mensaje": "Parada y continuamos por velázquez",
    "distancia_previa_metros": 110,
    "mensaje_previo": ""
  },
  {
    "tipo": "voz_personalizada",
    "direccion": "toB",
    "lat": 40.426841,
    "lng": -3.68401,
    "radio_metros": 60,
    "icono_sf": "arrow.up",
    "mensaje": "continuamos todo recto",
    "distancia_previa_metros": 110,
    "mensaje_previo": ""
  },
  {
    "tipo": "voz_personalizada",
    "direccion": "toB",
    "lat": 40.429536,
    "lng": -3.683781,
    "radio_metros": 60,
    "icono_sf": "arrow.up",
    "mensaje": "Parada y continuamos recto en dirección a maría de molina",
    "distancia_previa_metros": 110,
    "mensaje_previo": ""
  },
  {
    "tipo": "voz_personalizada",
    "direccion": "toB",
    "lat": 40.431864,
    "lng": -3.683607,
    "radio_metros": 60,
    "icono_sf": "arrow.up",
    "mensaje": "Parada y continuamos recto",
    "distancia_previa_metros": 110,
    "mensaje_previo": ""
  },
  {
    "tipo": "voz_personalizada",
    "direccion": "toB",
    "lat": 40.434268,
    "lng": -3.683409,
    "radio_metros": 60,
    "icono_sf": "arrow.up",
    "mensaje": "Parada continuamos recto hacia maría de molina",
    "distancia_previa_metros": 110,
    "mensaje_previo": ""
  },
  {
    "tipo": "voz_personalizada",
    "direccion": "toB",
    "lat": 40.435611,
    "lng": -3.683259,
    "radio_metros": 60,
    "icono_sf": "arrow.up",
    "mensaje": "continuamos recto por la izquierda dirección maría de molina",
    "distancia_previa_metros": 110,
    "mensaje_previo": ""
  },
  {
    "tipo": "voz_personalizada",
    "direccion": "toB",
    "lat": 40.437287,
    "lng": -3.683161,
    "radio_metros": 60,
    "icono_sf": "arrow.turn.up.right",
    "mensaje": "Giramos a la derecha por maría de molina ,después parada",
    "distancia_previa_metros": 110,
    "mensaje_previo": ""
  },
  {
    "tipo": "voz_personalizada",
    "direccion": "toB",
    "lat": 40.437599,
    "lng": -3.681688,
    "radio_metros": 60,
    "icono_sf": "arrow.up",
    "mensaje": "continuamos recto por maría de molina",
    "distancia_previa_metros": 110,
    "mensaje_previo": ""
  },
  {
    "tipo": "voz_personalizada",
    "direccion": "toB",
    "lat": 40.437504,
    "lng": -3.679897,
    "radio_metros": 60,
    "icono_sf": "arrow.up",
    "mensaje": "Parada y continuamos recto en dirección aeropuerto",
    "distancia_previa_metros": 110,
    "mensaje_previo": ""
  },
  {
    "tipo": "voz_personalizada",
    "direccion": "toB",
    "lat": 40.437393,
    "lng": -3.678033,
    "radio_metros": 60,
    "icono_sf": "arrow.up",
    "mensaje": "continuamos recto en el cruce dirección aeropuerto ,después parada",
    "distancia_previa_metros": 110,
    "mensaje_previo": ""
  },
  {
    "tipo": "voz_personalizada",
    "direccion": "toB",
    "lat": 40.437581,
    "lng": -3.676941,
    "radio_metros": 60,
    "icono_sf": "road.lanes",
    "mensaje": "Parada , entramos por el tunel en dirección aeropuerto",
    "distancia_previa_metros": 110,
    "mensaje_previo": ""
  },
  {
    "tipo": "voz_personalizada",
    "direccion": "toB",
    "lat": 40.438429,
    "lng": -3.675541,
    "radio_metros": 60,
    "icono_sf": "road.lanes",
    "mensaje": "Entramos po el tunel dirección aeropuerto",
    "distancia_previa_metros": 110,
    "mensaje_previo": ""
  },
  {
    "tipo": "voz_personalizada",
    "direccion": "toB",
    "lat": 40.439495,
    "lng": -3.671423,
    "radio_metros": 60,
    "icono_sf": "arrow.up",
    "mensaje": "En dirección aeropuerto",
    "distancia_previa_metros": 110,
    "mensaje_previo": ""
  },
  {
    "tipo": "voz_personalizada",
    "direccion": "toB",
    "lat": 40.440576,
    "lng": -3.668969,
    "radio_metros": 60,
    "icono_sf": "arrow.up",
    "mensaje": "En dirección aeropuerto",
    "distancia_previa_metros": 110,
    "mensaje_previo": ""
  },
  {
    "tipo": "voz_personalizada",
    "direccion": "toB",
    "lat": 40.442592,
    "lng": -3.665515,
    "radio_metros": 60,
    "icono_sf": "arrow.up",
    "mensaje": "Ahora vamos en dirección arturo soria",
    "distancia_previa_metros": 110,
    "mensaje_previo": ""
  },
  {
    "tipo": "voz_personalizada",
    "direccion": "toB",
    "lat": 40.44359,
    "lng": -3.663291,
    "radio_metros": 60,
    "icono_sf": "arrow.up",
    "mensaje": "En dirección arturo soria",
    "distancia_previa_metros": 110,
    "mensaje_previo": ""
  },
  {
    "tipo": "voz_personalizada",
    "direccion": "toB",
    "lat": 40.444514,
    "lng": -3.660705,
    "radio_metros": 60,
    "icono_sf": "road.lanes",
    "mensaje": "En dirección arturo soria entramos en tunel",
    "distancia_previa_metros": 110,
    "mensaje_previo": ""
  },
  {
    "tipo": "voz_personalizada",
    "direccion": "toB",
    "lat": 40.445053,
    "lng": -3.659173,
    "radio_metros": 60,
    "icono_sf": "road.lanes",
    "mensaje": "Entramos po el tunel",
    "distancia_previa_metros": 110,
    "mensaje_previo": ""
  },
  {
    "tipo": "voz_personalizada",
    "direccion": "toB",
    "lat": 40.445736,
    "lng": -3.657177,
    "radio_metros": 60,
    "icono_sf": "arrow.up",
    "mensaje": "Luego más adelante salimos por la izquierda solo bus",
    "distancia_previa_metros": 110,
    "mensaje_previo": ""
  },
  {
    "tipo": "voz_personalizada",
    "direccion": "toB",
    "lat": 40.446486,
    "lng": -3.654979,
    "radio_metros": 60,
    "icono_sf": "arrow.up",
    "mensaje": "Salimos por la izquierda solo bus , después parada",
    "distancia_previa_metros": 110,
    "mensaje_previo": ""
  },
  {
    "tipo": "voz_personalizada",
    "direccion": "toB",
    "lat": 40.447707,
    "lng": -3.65209,
    "radio_metros": 60,
    "icono_sf": "arrow.up",
    "mensaje": "Parada , continuando en dirección arturo soria",
    "distancia_previa_metros": 110,
    "mensaje_previo": ""
  },
  {
    "tipo": "voz_personalizada",
    "direccion": "toB",
    "lat": 40.44882,
    "lng": -3.649432,
    "radio_metros": 60,
    "icono_sf": "arrow.up",
    "mensaje": "Salimos por la derecha en dirección arturo soria",
    "distancia_previa_metros": 110,
    "mensaje_previo": ""
  },
  {
    "tipo": "voz_personalizada",
    "direccion": "toB",
    "lat": 40.449752,
    "lng": -3.646816,
    "radio_metros": 60,
    "icono_sf": "arrow.up",
    "mensaje": "Salimos por la derecha , nos mantenemos en carril izquierdo",
    "distancia_previa_metros": 110,
    "mensaje_previo": ""
  },
  {
    "tipo": "voz_personalizada",
    "direccion": "toB",
    "lat": 40.449262,
    "lng": -3.643707,
    "radio_metros": 60,
    "icono_sf": "arrow.turn.up.right",
    "mensaje": "Nos mantenemos a la derecha",
    "distancia_previa_metros": 110,
    "mensaje_previo": ""
  },
  {
    "tipo": "voz_personalizada",
    "direccion": "toB",
    "lat": 40.448904,
    "lng": -3.64135,
    "radio_metros": 60,
    "icono_sf": "arrow.up",
    "mensaje": "Parada y nos mantenemos en carril derecho",
    "distancia_previa_metros": 110,
    "mensaje_previo": ""
  },
  {
    "tipo": "voz_personalizada",
    "direccion": "toB",
    "lat": 40.448417,
    "lng": -3.638807,
    "radio_metros": 60,
    "icono_sf": "arrow.up",
    "mensaje": "Salimos por la derecha",
    "distancia_previa_metros": 110,
    "mensaje_previo": ""
  },
  {
    "tipo": "voz_personalizada",
    "direccion": "toB",
    "lat": 40.448102,
    "lng": -3.636798,
    "radio_metros": 60,
    "icono_sf": "arrow.turn.up.left",
    "mensaje": "En la glorieta giramos a izquierda tercera salida",
    "distancia_previa_metros": 110,
    "mensaje_previo": ""
  },
  {
    "tipo": "voz_personalizada",
    "direccion": "toB",
    "lat": 40.447218,
    "lng": -3.635811,
    "radio_metros": 60,
    "icono_sf": "arrow.up",
    "mensaje": "Parada y continuamos todo recto",
    "distancia_previa_metros": 110,
    "mensaje_previo": ""
  },
  {
    "tipo": "voz_personalizada",
    "direccion": "toB",
    "lat": 40.447642,
    "lng": -3.632876,
    "radio_metros": 60,
    "icono_sf": "arrow.up",
    "mensaje": "Parada y continuamos recto",
    "distancia_previa_metros": 110,
    "mensaje_previo": ""
  },
  {
    "tipo": "voz_personalizada",
    "direccion": "toB",
    "lat": 40.447919,
    "lng": -3.63059,
    "radio_metros": 60,
    "icono_sf": "arrow.up",
    "mensaje": "Parada y continuamos recto",
    "distancia_previa_metros": 110,
    "mensaje_previo": ""
  },
  {
    "tipo": "voz_personalizada",
    "direccion": "toB",
    "lat": 40.447794,
    "lng": -3.628977,
    "radio_metros": 60,
    "icono_sf": "arrow.up",
    "mensaje": "continuamos recto",
    "distancia_previa_metros": 110,
    "mensaje_previo": ""
  },
  {
    "tipo": "voz_personalizada",
    "direccion": "toB",
    "lat": 40.44762,
    "lng": -3.627095,
    "radio_metros": 60,
    "icono_sf": "arrow.up",
    "mensaje": "En la glorieta cogemos la segunda salida ,después parada",
    "distancia_previa_metros": 110,
    "mensaje_previo": ""
  },
  {
    "tipo": "voz_personalizada",
    "direccion": "toB",
    "lat": 40.4477,
    "lng": -3.625405,
    "radio_metros": 60,
    "icono_sf": "arrow.up",
    "mensaje": "Salimos de la glorieta en dirección aeropuerto ,después parada",
    "distancia_previa_metros": 110,
    "mensaje_previo": ""
  },
  {
    "tipo": "voz_personalizada",
    "direccion": "toB",
    "lat": 40.447746,
    "lng": -3.623465,
    "radio_metros": 60,
    "icono_sf": "arrow.up",
    "mensaje": "Parada , en la glorieta segunda salida en dirección aeropuerto",
    "distancia_previa_metros": 110,
    "mensaje_previo": ""
  },
  {
    "tipo": "voz_personalizada",
    "direccion": "toB",
    "lat": 40.448894,
    "lng": -3.620584,
    "radio_metros": 60,
    "icono_sf": "exclamationmark.triangle.fill",
    "mensaje": "continuamos recto y cuidado stop más adelante",
    "distancia_previa_metros": 110,
    "mensaje_previo": ""
  },
  {
    "tipo": "voz_personalizada",
    "direccion": "toB",
    "lat": 40.449516,
    "lng": -3.616715,
    "radio_metros": 60,
    "icono_sf": "arrow.up",
    "mensaje": "Parada , nos vamos al carríl izquierdo en dirección aeropuerto",
    "distancia_previa_metros": 110,
    "mensaje_previo": ""
  },
  {
    "tipo": "voz_personalizada",
    "direccion": "toB",
    "lat": 40.44951,
    "lng": -3.61457,
    "radio_metros": 60,
    "icono_sf": "arrow.up",
    "mensaje": "continuamos por al izquierda",
    "distancia_previa_metros": 110,
    "mensaje_previo": ""
  },
  {
    "tipo": "voz_personalizada",
    "direccion": "toB",
    "lat": 40.449483,
    "lng": -3.61058,
    "radio_metros": 60,
    "icono_sf": "arrow.up",
    "mensaje": "Parada , en glorieta segunda salida de frente en dirección zaragoza aeropuerto",
    "distancia_previa_metros": 110,
    "mensaje_previo": ""
  },
  {
    "tipo": "voz_personalizada",
    "direccion": "toB",
    "lat": 40.44961,
    "lng": -3.607084,
    "radio_metros": 60,
    "icono_sf": "arrow.up",
    "mensaje": "Salimos por la izquierda en dirección aeropuerto",
    "distancia_previa_metros": 110,
    "mensaje_previo": ""
  },
  {
    "tipo": "voz_personalizada",
    "direccion": "toB",
    "lat": 40.449936,
    "lng": -3.602421,
    "radio_metros": 60,
    "icono_sf": "arrow.turn.up.right",
    "mensaje": "Nos mantenemos a la derecha en dirección aeropuerto",
    "distancia_previa_metros": 110,
    "mensaje_previo": ""
  },
  {
    "tipo": "voz_personalizada",
    "direccion": "toB",
    "lat": 40.450118,
    "lng": -3.599226,
    "radio_metros": 60,
    "icono_sf": "arrow.up",
    "mensaje": "En dirección aeropuerto",
    "distancia_previa_metros": 110,
    "mensaje_previo": ""
  },
  {
    "tipo": "voz_personalizada",
    "direccion": "toB",
    "lat": 40.450058,
    "lng": -3.596653,
    "radio_metros": 60,
    "icono_sf": "arrow.up",
    "mensaje": "Salimos por la derecha en dirección aeropuerto",
    "distancia_previa_metros": 110,
    "mensaje_previo": ""
  },
  {
    "tipo": "voz_personalizada",
    "direccion": "toB",
    "lat": 40.449849,
    "lng": -3.592889,
    "radio_metros": 60,
    "icono_sf": "arrow.up",
    "mensaje": "Salimos por la izquierda en dirección aeropuerto",
    "distancia_previa_metros": 110,
    "mensaje_previo": ""
  },
  {
    "tipo": "voz_personalizada",
    "direccion": "toB",
    "lat": 40.449119,
    "lng": -3.58846,
    "radio_metros": 60,
    "icono_sf": "arrow.up",
    "mensaje": "En dirección alameda de osuna",
    "distancia_previa_metros": 110,
    "mensaje_previo": ""
  },
  {
    "tipo": "voz_personalizada",
    "direccion": "toB",
    "lat": 40.450267,
    "lng": -3.58731,
    "radio_metros": 60,
    "icono_sf": "arrow.up",
    "mensaje": "En dirección alameda de osuna",
    "distancia_previa_metros": 110,
    "mensaje_previo": ""
  },
  {
    "tipo": "voz_personalizada",
    "direccion": "toB",
    "lat": 40.452615,
    "lng": -3.58611,
    "radio_metros": 60,
    "icono_sf": "arrow.up",
    "mensaje": "Salimos por la derecha , después parada después inicio circuito neutralizado",
    "distancia_previa_metros": 110,
    "mensaje_previo": ""
  },
  {
    "tipo": "voz_personalizada",
    "direccion": "toB",
    "lat": 40.45313,
    "lng": -3.58445,
    "radio_metros": 60,
    "icono_sf": "arrow.up",
    "mensaje": "continuamos recto ligeramnete derecha , después parada",
    "distancia_previa_metros": 110,
    "mensaje_previo": ""
  },
  {
    "tipo": "voz_personalizada",
    "direccion": "toB",
    "lat": 40.452206,
    "lng": -3.584479,
    "radio_metros": 60,
    "icono_sf": "exclamationmark.triangle.fill",
    "mensaje": "Parada continuamos recto cuidado tramo estrecho",
    "distancia_previa_metros": 110,
    "mensaje_previo": ""
  },
  {
    "tipo": "voz_personalizada",
    "direccion": "toB",
    "lat": 40.450571,
    "lng": -3.584559,
    "radio_metros": 60,
    "icono_sf": "arrow.up",
    "mensaje": "Abrete bién giro estrecho",
    "distancia_previa_metros": 110,
    "mensaje_previo": ""
  },
  {
    "tipo": "voz_personalizada",
    "direccion": "toB",
    "lat": 40.452576,
    "lng": -3.5812,
    "radio_metros": 60,
    "icono_sf": "arrow.turn.up.left",
    "mensaje": "Nos mantenemos a la izquierda y en glorieta segunda salida",
    "distancia_previa_metros": 110,
    "mensaje_previo": ""
  },
  {
    "tipo": "voz_personalizada",
    "direccion": "toB",
    "lat": 40.450352,
    "lng": -3.582327,
    "radio_metros": 60,
    "icono_sf": "exclamationmark.triangle.fill",
    "mensaje": "Cuidado badenes y en el stop giramos a la izquierda",
    "distancia_previa_metros": 110,
    "mensaje_previo": ""
  },
  {
    "tipo": "voz_personalizada",
    "direccion": "toB",
    "lat": 40.451179,
    "lng": -3.581263,
    "radio_metros": 60,
    "icono_sf": "arrow.up",
    "mensaje": "Parada y continuamos recto",
    "distancia_previa_metros": 110,
    "mensaje_previo": ""
  },
  {
    "tipo": "voz_personalizada",
    "direccion": "toB",
    "lat": 40.45427,
    "lng": -3.582665,
    "radio_metros": 60,
    "icono_sf": "arrow.up",
    "mensaje": "En la glorieta segunda salida en dirección alameda de osuna",
    "distancia_previa_metros": 110,
    "mensaje_previo": ""
  },
  {
    "tipo": "voz_personalizada",
    "direccion": "toB",
    "lat": 40.456916,
    "lng": -3.584205,
    "radio_metros": 60,
    "icono_sf": "arrow.up",
    "mensaje": "En la glorieta segunda salida",
    "distancia_previa_metros": 110,
    "mensaje_previo": ""
  },
  {
    "tipo": "voz_personalizada",
    "direccion": "toB",
    "lat": 40.457582,
    "lng": -3.582082,
    "radio_metros": 60,
    "icono_sf": "arrow.up",
    "mensaje": "Por la izquierda y en glorieta tercera salida , después parada",
    "distancia_previa_metros": 110,
    "mensaje_previo": ""
  },
  {
    "tipo": "voz_personalizada",
    "direccion": "toB",
    "lat": 40.459331,
    "lng": -3.582271,
    "radio_metros": 60,
    "icono_sf": "arrow.up",
    "mensaje": "En la glorieta cuarta salida , después parada",
    "distancia_previa_metros": 110,
    "mensaje_previo": ""
  },
  {
    "tipo": "voz_personalizada",
    "direccion": "toB",
    "lat": 40.457242,
    "lng": -3.585756,
    "radio_metros": 60,
    "icono_sf": "arrow.up",
    "mensaje": "Parada y continuamos recto",
    "distancia_previa_metros": 110,
    "mensaje_previo": ""
  },
  {
    "tipo": "voz_personalizada",
    "direccion": "toB",
    "lat": 40.456958,
    "lng": -3.586772,
    "radio_metros": 60,
    "icono_sf": "arrow.turn.up.right",
    "mensaje": "Giramos a la derecha en el cruce",
    "distancia_previa_metros": 110,
    "mensaje_previo": ""
  },
  {
    "tipo": "voz_personalizada",
    "direccion": "toB",
    "lat": 40.458348,
    "lng": -3.588901,
    "radio_metros": 60,
    "icono_sf": "arrow.turn.up.right",
    "mensaje": "Giramos a derecha por paseo alameda de osuna",
    "distancia_previa_metros": 110,
    "mensaje_previo": ""
  },
  {
    "tipo": "voz_personalizada",
    "direccion": "toB",
    "lat": 40.459271,
    "lng": -3.588088,
    "radio_metros": 60,
    "icono_sf": "arrow.turn.up.left",
    "mensaje": "Parada y más adelante giramos a la izquierda",
    "distancia_previa_metros": 110,
    "mensaje_previo": ""
  },
  {
    "tipo": "voz_personalizada",
    "direccion": "toB",
    "lat": 40.460169,
    "lng": -3.586914,
    "radio_metros": 60,
    "icono_sf": "arrow.turn.up.left",
    "mensaje": "Giramos a la izquierda ábrete bien tramo estrecho",
    "distancia_previa_metros": 110,
    "mensaje_previo": ""
  },
  {
    "tipo": "voz_personalizada",
    "direccion": "toB",
    "lat": 40.460924,
    "lng": -3.587802,
    "radio_metros": 60,
    "icono_sf": "arrow.up",
    "mensaje": "continuamos recto por el carril derecho",
    "distancia_previa_metros": 110,
    "mensaje_previo": ""
  },
  {
    "tipo": "voz_personalizada",
    "direccion": "toB",
    "lat": 40.461511,
    "lng": -3.589021,
    "radio_metros": 60,
    "icono_sf": "light.beacon.max.fill",
    "mensaje": "Giramos a derecha en semáforo",
    "distancia_previa_metros": 110,
    "mensaje_previo": ""
  },
  {
    "tipo": "voz_personalizada",
    "direccion": "toB",
    "lat": 40.462797,
    "lng": -3.588177,
    "radio_metros": 60,
    "icono_sf": "arrow.up",
    "mensaje": "Parada y continuamos todo recto",
    "distancia_previa_metros": 110,
    "mensaje_previo": ""
  },
  {
    "tipo": "voz_personalizada",
    "direccion": "toB",
    "lat": 40.464049,
    "lng": -3.586312,
    "radio_metros": 60,
    "icono_sf": "arrow.up",
    "mensaje": "continuamos recto , después parada",
    "distancia_previa_metros": 110,
    "mensaje_previo": ""
  },
  {
    "tipo": "voz_personalizada",
    "direccion": "toB",
    "lat": 40.465966,
    "lng": -3.583473,
    "radio_metros": 60,
    "icono_sf": "arrow.up",
    "mensaje": "En la glorieta segunda salida en dirección avenida general",
    "distancia_previa_metros": 110,
    "mensaje_previo": ""
  },
  {
    "tipo": "voz_personalizada",
    "direccion": "toB",
    "lat": 40.468076,
    "lng": -3.58183,
    "radio_metros": 60,
    "icono_sf": "arrow.up",
    "mensaje": "Salimos de glorieta en dirección avenida general , después parada",
    "distancia_previa_metros": 110,
    "mensaje_previo": ""
  },
  {
    "tipo": "voz_personalizada",
    "direccion": "toB",
    "lat": 40.468887,
    "lng": -3.581459,
    "radio_metros": 60,
    "icono_sf": "arrow.up",
    "mensaje": "continuamos recto por el carríl derecho hacia avenida general",
    "distancia_previa_metros": 110,
    "mensaje_previo": ""
  },
  {
    "tipo": "voz_personalizada",
    "direccion": "toB",
    "lat": 40.449497,
    "lng": -3.645318,
    "radio_metros": 60,
    "icono_sf": "arrow.turn.up.left",
    "mensaje": "Giramos a izquierda continuamos por via de servicio",
    "distancia_previa_metros": 110,
    "mensaje_previo": ""
  },
  {
    "tipo": "voz_personalizada",
    "direccion": "toB",
    "lat": 40.457171,
    "lng": -3.587989,
    "radio_metros": 60,
    "icono_sf": "arrow.up",
    "mensaje": "Parada junto al metro y continuamos recto",
    "distancia_previa_metros": 110,
    "mensaje_previo": ""
  },
  {
    "tipo": "voz_personalizada",
    "direccion": "toB",
    "lat": 40.47025,
    "lng": -3.580668,
    "radio_metros": 60,
    "icono_sf": "arrow.up",
    "mensaje": "continuamos por el carril derecho por avenida general , después parada en la gasolinera",
    "distancia_previa_metros": 110,
    "mensaje_previo": ""
  },
  {
    "tipo": "voz_personalizada",
    "direccion": "toB",
    "lat": 40.472269,
    "lng": -3.5789,
    "radio_metros": 60,
    "icono_sf": "arrow.up",
    "mensaje": "Por avenida general en ambos sentidos seguimos la linea de la ruta",
    "distancia_previa_metros": 110,
    "mensaje_previo": ""
  },
  {
    "tipo": "voz_personalizada",
    "direccion": "toB",
    "lat": 40.473583,
    "lng": -3.577106,
    "radio_metros": 60,
    "icono_sf": "arrow.up",
    "mensaje": "Parada y salimos de nuevo por avenida general por la farmacia",
    "distancia_previa_metros": 110,
    "mensaje_previo": ""
  },
  {
    "tipo": "voz_personalizada",
    "direccion": "toB",
    "lat": 40.47403,
    "lng": -3.57754,
    "radio_metros": 60,
    "icono_sf": "arrow.turn.up.right",
    "mensaje": "Salimos por la farmacia y no hay mas avisos hasta girar en caixabank a la derecha",
    "distancia_previa_metros": 110,
    "mensaje_previo": ""
  },
  {
    "tipo": "voz_personalizada",
    "direccion": "toB",
    "lat": 40.47149,
    "lng": -3.581495,
    "radio_metros": 60,
    "icono_sf": "light.beacon.max.fill",
    "mensaje": "En el semáforo giramos a la derecha , después parada",
    "distancia_previa_metros": 110,
    "mensaje_previo": ""
  },
  {
    "tipo": "voz_personalizada",
    "direccion": "toB",
    "lat": 40.473226,
    "lng": -3.582055,
    "radio_metros": 60,
    "icono_sf": "arrow.up",
    "mensaje": "continuamos recto",
    "distancia_previa_metros": 110,
    "mensaje_previo": ""
  },
  {
    "tipo": "voz_personalizada",
    "direccion": "toB",
    "lat": 40.474806,
    "lng": -3.582398,
    "radio_metros": 60,
    "icono_sf": "light.beacon.max.fill",
    "mensaje": "En semáforo giramos a izquierda y final de línea junto al metro",
    "distancia_previa_metros": 110,
    "mensaje_previo": ""
  },
  {
    "tipo": "voz_personalizada",
    "direccion": "toB",
    "lat": 40.47563,
    "lng": -3.58285,
    "radio_metros": 60,
    "icono_sf": "arrow.up",
    "mensaje": "Final de línea junto al metro  continuamos con circuito neutralizado",
    "distancia_previa_metros": 110,
    "mensaje_previo": ""
  }
]