[
  {
    "tipo": "voz_personalizada",
    "direccion": "toB",
    "lat": 40.390565,
    "lng": -3.694042,
    "radio_metros": 60,
    "icono_sf": "arrow.up",
    "mensaje": "Línea 180 en sentido pozo del tío raimundo inicio y continuamos recto",
    "distancia_previa_metros": 110,
    "mensaje_previo": ""
  },
  {
    "tipo": "voz_personalizada",
    "direccion": "toB",
    "lat": 40.389956,
    "lng": -3.692944,
    "radio_metros": 60,
    "icono_sf": "arrow.up",
    "mensaje": "continuamos recto en dirección caja mágica",
    "distancia_previa_metros": 110,
    "mensaje_previo": ""
  },
  {
    "tipo": "voz_personalizada",
    "direccion": "toB",
    "lat": 40.389122,
    "lng": -3.691796,
    "radio_metros": 60,
    "icono_sf": "arrow.up",
    "mensaje": "En dirección caja mágica",
    "distancia_previa_metros": 110,
    "mensaje_previo": ""
  },
  {
    "tipo": "voz_personalizada",
    "direccion": "toB",
    "lat": 40.388088,
    "lng": -3.691204,
    "radio_metros": 60,
    "icono_sf": "arrow.up",
    "mensaje": "Parada  continuamos recto en dirección caja mágica",
    "distancia_previa_metros": 110,
    "mensaje_previo": ""
  },
  {
    "tipo": "voz_personalizada",
    "direccion": "toB",
    "lat": 40.387128,
    "lng": -3.69052,
    "radio_metros": 60,
    "icono_sf": "arrow.up",
    "mensaje": "En dirección caja mágica y después parada debajo del puente",
    "distancia_previa_metros": 110,
    "mensaje_previo": ""
  },
  {
    "tipo": "voz_personalizada",
    "direccion": "toB",
    "lat": 40.385891,
    "lng": -3.689469,
    "radio_metros": 60,
    "icono_sf": "arrow.up",
    "mensaje": "continuamos recto siempre dirección caja mágica",
    "distancia_previa_metros": 110,
    "mensaje_previo": ""
  },
  {
    "tipo": "voz_personalizada",
    "direccion": "toB",
    "lat": 40.385112,
    "lng": -3.688531,
    "radio_metros": 60,
    "icono_sf": "arrow.up",
    "mensaje": "En dirección caja mágica subimos por el puente",
    "distancia_previa_metros": 110,
    "mensaje_previo": ""
  },
  {
    "tipo": "voz_personalizada",
    "direccion": "toB",
    "lat": 40.383613,
    "lng": -3.687246,
    "radio_metros": 60,
    "icono_sf": "arrow.up",
    "mensaje": "continuamos todo recto",
    "distancia_previa_metros": 110,
    "mensaje_previo": ""
  },
  {
    "tipo": "voz_personalizada",
    "direccion": "toB",
    "lat": 40.381658,
    "lng": -3.685782,
    "radio_metros": 60,
    "icono_sf": "arrow.up",
    "mensaje": "continuamos todo recto",
    "distancia_previa_metros": 110,
    "mensaje_previo": ""
  },
  {
    "tipo": "voz_personalizada",
    "direccion": "toB",
    "lat": 40.380114,
    "lng": -3.684775,
    "radio_metros": 60,
    "icono_sf": "arrow.up",
    "mensaje": "continuamos todo recto",
    "distancia_previa_metros": 110,
    "mensaje_previo": ""
  },
  {
    "tipo": "voz_personalizada",
    "direccion": "toB",
    "lat": 40.378371,
    "lng": -3.683679,
    "radio_metros": 60,
    "icono_sf": "arrow.up",
    "mensaje": "continuamos recto y después parada",
    "distancia_previa_metros": 110,
    "mensaje_previo": ""
  },
  {
    "tipo": "voz_personalizada",
    "direccion": "toB",
    "lat": 40.375273,
    "lng": -3.681957,
    "radio_metros": 60,
    "icono_sf": "arrow.up",
    "mensaje": "En la glorieta parada y después segunda salida en dirección m 40 m 40",
    "distancia_previa_metros": 110,
    "mensaje_previo": ""
  },
  {
    "tipo": "voz_personalizada",
    "direccion": "toB",
    "lat": 40.374062,
    "lng": -3.682097,
    "radio_metros": 60,
    "icono_sf": "arrow.up",
    "mensaje": "Parada  después salimos de la glorieta en direccion m 40",
    "distancia_previa_metros": 110,
    "mensaje_previo": ""
  },
  {
    "tipo": "voz_personalizada",
    "direccion": "toB",
    "lat": 40.371698,
    "lng": -3.680705,
    "radio_metros": 60,
    "icono_sf": "arrow.up",
    "mensaje": "continuamos recto dirección m 40",
    "distancia_previa_metros": 110,
    "mensaje_previo": ""
  },
  {
    "tipo": "voz_personalizada",
    "direccion": "toB",
    "lat": 40.370348,
    "lng": -3.680161,
    "radio_metros": 60,
    "icono_sf": "arrow.up",
    "mensaje": "Parada y nos mantenemos en carril izquierdo pasando por debajo del puente",
    "distancia_previa_metros": 110,
    "mensaje_previo": ""
  },
  {
    "tipo": "voz_personalizada",
    "direccion": "toB",
    "lat": 40.36906,
    "lng": -3.678952,
    "radio_metros": 60,
    "icono_sf": "road.lanes",
    "mensaje": "Circula por el centro del tunel",
    "distancia_previa_metros": 110,
    "mensaje_previo": ""
  },
  {
    "tipo": "voz_personalizada",
    "direccion": "toB",
    "lat": 40.369369,
    "lng": -3.677046,
    "radio_metros": 60,
    "icono_sf": "arrow.up",
    "mensaje": "Nos mantenemos a derecha y continuamos recto",
    "distancia_previa_metros": 110,
    "mensaje_previo": ""
  },
  {
    "tipo": "voz_personalizada",
    "direccion": "toB",
    "lat": 40.368427,
    "lng": -3.675267,
    "radio_metros": 60,
    "icono_sf": "arrow.turn.up.left",
    "mensaje": "Parada  después al final de calle giramos a izquierda",
    "distancia_previa_metros": 110,
    "mensaje_previo": ""
  },
  {
    "tipo": "voz_personalizada",
    "direccion": "toB",
    "lat": 40.366805,
    "lng": -3.673733,
    "radio_metros": 60,
    "icono_sf": "arrow.turn.up.left",
    "mensaje": "Giramos a izquierda al final de calle",
    "distancia_previa_metros": 110,
    "mensaje_previo": ""
  },
  {
    "tipo": "voz_personalizada",
    "direccion": "toB",
    "lat": 40.367002,
    "lng": -3.670717,
    "radio_metros": 60,
    "icono_sf": "arrow.up",
    "mensaje": "continuamos todo recto",
    "distancia_previa_metros": 110,
    "mensaje_previo": ""
  },
  {
    "tipo": "voz_personalizada",
    "direccion": "toB",
    "lat": 40.367664,
    "lng": -3.66794,
    "radio_metros": 60,
    "icono_sf": "arrow.up",
    "mensaje": "continuamos recto",
    "distancia_previa_metros": 110,
    "mensaje_previo": ""
  },
  {
    "tipo": "voz_personalizada",
    "direccion": "toB",
    "lat": 40.36783,
    "lng": -3.665398,
    "radio_metros": 60,
    "icono_sf": "arrow.up",
    "mensaje": "Parada y después en glorieta tercera salida en dirección camino de la celsa",
    "distancia_previa_metros": 110,
    "mensaje_previo": ""
  },
  {
    "tipo": "voz_personalizada",
    "direccion": "toB",
    "lat": 40.367589,
    "lng": -3.663674,
    "radio_metros": 60,
    "icono_sf": "arrow.up",
    "mensaje": "En glorieta tercera salida dirección camino de la celsa",
    "distancia_previa_metros": 110,
    "mensaje_previo": ""
  },
  {
    "tipo": "voz_personalizada",
    "direccion": "toB",
    "lat": 40.369889,
    "lng": -3.662466,
    "radio_metros": 60,
    "icono_sf": "arrow.turn.up.right",
    "mensaje": "Al final de calle giramos a derecha",
    "distancia_previa_metros": 110,
    "mensaje_previo": ""
  },
  {
    "tipo": "voz_personalizada",
    "direccion": "toB",
    "lat": 40.369716,
    "lng": -3.660308,
    "radio_metros": 60,
    "icono_sf": "exclamationmark.triangle.fill",
    "mensaje": "atención giro cerrado a izquierda",
    "distancia_previa_metros": 110,
    "mensaje_previo": ""
  },
  {
    "tipo": "voz_personalizada",
    "direccion": "toB",
    "lat": 40.37092,
    "lng": -3.659167,
    "radio_metros": 60,
    "icono_sf": "arrow.up",
    "mensaje": "continuamos recto hasta final de calle",
    "distancia_previa_metros": 110,
    "mensaje_previo": ""
  },
  {
    "tipo": "voz_personalizada",
    "direccion": "toB",
    "lat": 40.372984,
    "lng": -3.658113,
    "radio_metros": 60,
    "icono_sf": "arrow.turn.up.left",
    "mensaje": "Parada y después al final de calle giramos a izquierda",
    "distancia_previa_metros": 110,
    "mensaje_previo": ""
  },
  {
    "tipo": "voz_personalizada",
    "direccion": "toB",
    "lat": 40.374771,
    "lng": -3.657136,
    "radio_metros": 60,
    "icono_sf": "mappin.circle.fill",
    "mensaje": "Al final de calle giramos a izquierda y después cabecera de línea",
    "distancia_previa_metros": 110,
    "mensaje_previo": ""
  },
  {
    "tipo": "voz_personalizada",
    "direccion": "toB",
    "lat": 40.37543,
    "lng": -3.657559,
    "radio_metros": 60,
    "icono_sf": "arrow.up",
    "mensaje": "Final de línea",
    "distancia_previa_metros": 110,
    "mensaje_previo": ""
  },
  {
    "tipo": "voz_personalizada",
    "direccion": "toA",
    "lat": 40.375568,
    "lng": -3.657969,
    "radio_metros": 60,
    "icono_sf": "arrow.turn.up.left",
    "mensaje": "Línea 180 en sentido plaza de legazpi inicio y después de pasar la glorieta giramos a izquierda por calle vecinos del pozo",
    "distancia_previa_metros": 110,
    "mensaje_previo": ""
  },
  {
    "tipo": "voz_personalizada",
    "direccion": "toA",
    "lat": 40.375915,
    "lng": -3.659282,
    "radio_metros": 60,
    "icono_sf": "arrow.turn.up.left",
    "mensaje": "Giramos a izquierda por calle vecinos del pozo",
    "distancia_previa_metros": 110,
    "mensaje_previo": ""
  },
  {
    "tipo": "voz_personalizada",
    "direccion": "toA",
    "lat": 40.374975,
    "lng": -3.659819,
    "radio_metros": 60,
    "icono_sf": "arrow.up",
    "mensaje": "Parada  continuamos recto hasta final de calle",
    "distancia_previa_metros": 110,
    "mensaje_previo": ""
  },
  {
    "tipo": "voz_personalizada",
    "direccion": "toA",
    "lat": 40.373712,
    "lng": -3.660543,
    "radio_metros": 60,
    "icono_sf": "arrow.turn.up.left",
    "mensaje": "Giramos a izquierda  después a derecha y parada",
    "distancia_previa_metros": 110,
    "mensaje_previo": ""
  },
  {
    "tipo": "voz_personalizada",
    "direccion": "toA",
    "lat": 40.372464,
    "lng": -3.660902,
    "radio_metros": 60,
    "icono_sf": "arrow.up",
    "mensaje": "continuamos recto hasta final de calle",
    "distancia_previa_metros": 110,
    "mensaje_previo": ""
  },
  {
    "tipo": "voz_personalizada",
    "direccion": "toA",
    "lat": 40.370931,
    "lng": -3.661777,
    "radio_metros": 60,
    "icono_sf": "arrow.turn.up.left",
    "mensaje": "Al final de calle giramos a izquierda  seguidamente a derecha",
    "distancia_previa_metros": 110,
    "mensaje_previo": ""
  },
  {
    "tipo": "voz_personalizada",
    "direccion": "toA",
    "lat": 40.369791,
    "lng": -3.662568,
    "radio_metros": 60,
    "icono_sf": "arrow.up",
    "mensaje": "continuamos recto siempre dirección embajadores",
    "distancia_previa_metros": 110,
    "mensaje_previo": ""
  },
  {
    "tipo": "voz_personalizada",
    "direccion": "toA",
    "lat": 40.368634,
    "lng": -3.663341,
    "radio_metros": 60,
    "icono_sf": "arrow.up",
    "mensaje": "En glorieta primera salida a derecha dirección embajadores y después parada",
    "distancia_previa_metros": 110,
    "mensaje_previo": ""
  },
  {
    "tipo": "voz_personalizada",
    "direccion": "toA",
    "lat": 40.367819,
    "lng": -3.664161,
    "radio_metros": 60,
    "icono_sf": "arrow.up",
    "mensaje": "En dirección embajadores  después parada",
    "distancia_previa_metros": 110,
    "mensaje_previo": ""
  },
  {
    "tipo": "voz_personalizada",
    "direccion": "toA",
    "lat": 40.367686,
    "lng": -3.667586,
    "radio_metros": 60,
    "icono_sf": "arrow.up",
    "mensaje": "continuamos recto",
    "distancia_previa_metros": 110,
    "mensaje_previo": ""
  },
  {
    "tipo": "voz_personalizada",
    "direccion": "toA",
    "lat": 40.367279,
    "lng": -3.669826,
    "radio_metros": 60,
    "icono_sf": "arrow.up",
    "mensaje": "continuamos recto dirección embajadores",
    "distancia_previa_metros": 110,
    "mensaje_previo": ""
  },
  {
    "tipo": "voz_personalizada",
    "direccion": "toA",
    "lat": 40.366611,
    "lng": -3.671942,
    "radio_metros": 60,
    "icono_sf": "light.beacon.max.fill",
    "mensaje": "Giramos a derecha en semáforo dirección embajadores",
    "distancia_previa_metros": 110,
    "mensaje_previo": ""
  },
  {
    "tipo": "voz_personalizada",
    "direccion": "toA",
    "lat": 40.367441,
    "lng": -3.674239,
    "radio_metros": 60,
    "icono_sf": "arrow.up",
    "mensaje": "Parada  continuamos todo recto",
    "distancia_previa_metros": 110,
    "mensaje_previo": ""
  },
  {
    "tipo": "voz_personalizada",
    "direccion": "toA",
    "lat": 40.368895,
    "lng": -3.675872,
    "radio_metros": 60,
    "icono_sf": "arrow.up",
    "mensaje": "En el cruce continuamos recto por debajo del puente dirección caja mágica",
    "distancia_previa_metros": 110,
    "mensaje_previo": ""
  },
  {
    "tipo": "voz_personalizada",
    "direccion": "toA",
    "lat": 40.369299,
    "lng": -3.677508,
    "radio_metros": 60,
    "icono_sf": "road.lanes",
    "mensaje": "Circulamos por el centro dentro del tunel",
    "distancia_previa_metros": 110,
    "mensaje_previo": ""
  },
  {
    "tipo": "voz_personalizada",
    "direccion": "toA",
    "lat": 40.369275,
    "lng": -3.679526,
    "radio_metros": 60,
    "icono_sf": "arrow.up",
    "mensaje": "Nos mantenemos a derecha continuamos recto",
    "distancia_previa_metros": 110,
    "mensaje_previo": ""
  },
  {
    "tipo": "voz_personalizada",
    "direccion": "toA",
    "lat": 40.370489,
    "lng": -3.68022,
    "radio_metros": 60,
    "icono_sf": "arrow.up",
    "mensaje": "Parada y continuamos todo recto",
    "distancia_previa_metros": 110,
    "mensaje_previo": ""
  },
  {
    "tipo": "voz_personalizada",
    "direccion": "toA",
    "lat": 40.372177,
    "lng": -3.680883,
    "radio_metros": 60,
    "icono_sf": "arrow.up",
    "mensaje": "En la glorieta primera salida",
    "distancia_previa_metros": 110,
    "mensaje_previo": ""
  },
  {
    "tipo": "voz_personalizada",
    "direccion": "toA",
    "lat": 40.373895,
    "lng": -3.681041,
    "radio_metros": 60,
    "icono_sf": "arrow.up",
    "mensaje": "Salimos de la glorieta y después parada",
    "distancia_previa_metros": 110,
    "mensaje_previo": ""
  },
  {
    "tipo": "voz_personalizada",
    "direccion": "toA",
    "lat": 40.37527,
    "lng": -3.681955,
    "radio_metros": 60,
    "icono_sf": "arrow.up",
    "mensaje": "En dirección plaza de legazpi continuamos recto",
    "distancia_previa_metros": 110,
    "mensaje_previo": ""
  },
  {
    "tipo": "voz_personalizada",
    "direccion": "toA",
    "lat": 40.376448,
    "lng": -3.682578,
    "radio_metros": 60,
    "icono_sf": "arrow.turn.up.left",
    "mensaje": "Nos mantenemos a la izquierda en direccion plaza de legazpi",
    "distancia_previa_metros": 110,
    "mensaje_previo": ""
  },
  {
    "tipo": "voz_personalizada",
    "direccion": "toA",
    "lat": 40.377424,
    "lng": -3.683152,
    "radio_metros": 60,
    "icono_sf": "arrow.up",
    "mensaje": "Parada  cogemos carril izquierdo en dirección plaza de legazpi",
    "distancia_previa_metros": 110,
    "mensaje_previo": ""
  },
  {
    "tipo": "voz_personalizada",
    "direccion": "toA",
    "lat": 40.378666,
    "lng": -3.683845,
    "radio_metros": 60,
    "icono_sf": "arrow.up",
    "mensaje": "Por la izquierda siempre en dirección plaza de legazpi",
    "distancia_previa_metros": 110,
    "mensaje_previo": ""
  },
  {
    "tipo": "voz_personalizada",
    "direccion": "toA",
    "lat": 40.379981,
    "lng": -3.684685,
    "radio_metros": 60,
    "icono_sf": "arrow.up",
    "mensaje": "continuamos recto plaza de legazpi",
    "distancia_previa_metros": 110,
    "mensaje_previo": ""
  },
  {
    "tipo": "voz_personalizada",
    "direccion": "toA",
    "lat": 40.381805,
    "lng": -3.685877,
    "radio_metros": 60,
    "icono_sf": "arrow.up",
    "mensaje": "continuamos todo recto plaza de legazpi",
    "distancia_previa_metros": 110,
    "mensaje_previo": ""
  },
  {
    "tipo": "voz_personalizada",
    "direccion": "toA",
    "lat": 40.38315,
    "lng": -3.686876,
    "radio_metros": 60,
    "icono_sf": "arrow.up",
    "mensaje": "continuamos todo recto",
    "distancia_previa_metros": 110,
    "mensaje_previo": ""
  },
  {
    "tipo": "voz_personalizada",
    "direccion": "toA",
    "lat": 40.384729,
    "lng": -3.688098,
    "radio_metros": 60,
    "icono_sf": "arrow.up",
    "mensaje": "continuamos todo recto",
    "distancia_previa_metros": 110,
    "mensaje_previo": ""
  },
  {
    "tipo": "voz_personalizada",
    "direccion": "toA",
    "lat": 40.385713,
    "lng": -3.689119,
    "radio_metros": 60,
    "icono_sf": "arrow.up",
    "mensaje": "continuamos recto por debajo del puente  después parada",
    "distancia_previa_metros": 110,
    "mensaje_previo": ""
  },
  {
    "tipo": "voz_personalizada",
    "direccion": "toA",
    "lat": 40.386613,
    "lng": -3.689977,
    "radio_metros": 60,
    "icono_sf": "arrow.up",
    "mensaje": "Parada  continuamos dirección plaza de legazpi",
    "distancia_previa_metros": 110,
    "mensaje_previo": ""
  },
  {
    "tipo": "voz_personalizada",
    "direccion": "toA",
    "lat": 40.387629,
    "lng": -3.690801,
    "radio_metros": 60,
    "icono_sf": "arrow.up",
    "mensaje": "Parada  después continuamos recto por carril izquierdo dirección plaza de legazpi",
    "distancia_previa_metros": 110,
    "mensaje_previo": ""
  },
  {
    "tipo": "voz_personalizada",
    "direccion": "toA",
    "lat": 40.389029,
    "lng": -3.691588,
    "radio_metros": 60,
    "icono_sf": "arrow.up",
    "mensaje": "continuamos por la izquierda en dirección plaza de legazpi",
    "distancia_previa_metros": 110,
    "mensaje_previo": ""
  },
  {
    "tipo": "voz_personalizada",
    "direccion": "toA",
    "lat": 40.389981,
    "lng": -3.692989,
    "radio_metros": 60,
    "icono_sf": "arrow.uturn.down",
    "mensaje": "Antes de cruzar plaza de legazpi parada y después hacemos un cambio de sentido sigue la linea de la ruta",
    "distancia_previa_metros": 110,
    "mensaje_previo": ""
  },
  {
    "tipo": "voz_personalizada",
    "direccion": "toA",
    "lat": 40.391333,
    "lng": -3.695017,
    "radio_metros": 60,
    "icono_sf": "arrow.uturn.down",
    "mensaje": "Cambio de sentido en dirección a planetario  después fínal de línea",
    "distancia_previa_metros": 110,
    "mensaje_previo": ""
  },
  {
    "tipo": "voz_personalizada",
    "direccion": "toA",
    "lat": 40.39095,
    "lng": -3.695319,
    "radio_metros": 60,
    "icono_sf": "arrow.uturn.down",
    "mensaje": "Cambio de sentido en dirección a planetario y fínal de línea de",
    "distancia_previa_metros": 110,
    "mensaje_previo": ""
  }
]